setup.py
container_decrypter/__init__.py
container_decrypter/dlc.py
container_decrypter.egg-info/PKG-INFO
container_decrypter.egg-info/SOURCES.txt
container_decrypter.egg-info/dependency_links.txt
container_decrypter.egg-info/requires.txt
container_decrypter.egg-info/top_level.txt